{
    "state": "ok",
    "data": {
        "list": [
            {
                "name": "Unit2 I'm more outgoing to 2d",
                "type": "句子测评",
                "time": "2018/5/4 10:31",
                "progress": "10/14"
            },
            {
                "name": "Unit2 I'm more outgoing to 2d",
                "type": "句子测评",
                "time": "2018/5/4 10:31",
                "progress": "10/14"
            },
            {
                "name": "Unit2 I'm more outgoing to 2d",
                "type": "单词测评",
                "time": "2018/5/4 10:31",
                "progress": "10/14"
            },
            {
                "name": "Unit2 I'm more outgoing to 2d",
                "type": "句子测评",
                "time": "2018/5/4 10:31",
                "progress": "10/14"
            },
            {
                "name": "Unit2 I'm more outgoing to 2d",
                "type": "单词测评",
                "time": "2018/5/4 10:31",
                "progress": "10/14"
            },
            {
                "name": "Unit2 I'm more outgoing to 2d",
                "type": "句子测评",
                "time": "2018/5/4 10:31",
                "progress": "10/14"
            },
            {
                "name": "Unit2 I'm more outgoing to 2d",
                "type": "单词测评",
                "time": "2018/5/4 10:31",
                "progress": "10/14"
            },
            {
                "name": "Unit2 I'm more outgoing to 2d",
                "type": "句子测评",
                "time": "2018/5/4 10:31",
                "progress": "10/14"
            },
            {
                "name": "Unit2 I'm more outgoing to 2d",
                "type": "单词测评",
                "time": "2018/5/4 10:31",
                "progress": "10/14"
            },
            {
                "name": "Unit2 I'm more outgoing to 2d",
                "type": "句子测评",
                "time": "2018/5/4 10:31",
                "progress": "10/14"
            },
            {
                "name": "Unit2 I'm more outgoing to 2d",
                "type": "句子测评",
                "time": "2018/5/4 10:31",
                "progress": "10/14"
            }
        ],
        "page": {
            "cur": 1,
            "total": 12
        }
    }
}